sadptprj_riclyap_adi/__init__.py
sadptprj_riclyap_adi/bal_trunc_utils.py
sadptprj_riclyap_adi/lin_alg_utils.py
sadptprj_riclyap_adi/proj_ric_utils.py
sadptprj_riclyap_adi/schur_sadpoint_utils.py
sadptprj_riclyap_adi-1.0.5.dist-info/LICENSE
sadptprj_riclyap_adi-1.0.5.dist-info/METADATA
sadptprj_riclyap_adi-1.0.5.dist-info/WHEEL
sadptprj_riclyap_adi-1.0.5.dist-info/pbr.json
sadptprj_riclyap_adi-1.0.5.dist-info/top_level.txt
sadptprj_riclyap_adi-1.0.5.dist-info/RECORD
